OpenFisca_Web_API-8.2.0.data/data/share/locale/fr/LC_MESSAGES/openfisca-web-api.mo
OpenFisca_Web_API-8.2.0.data/data/share/openfisca/openfisca-web-api/CHANGELOG.md
OpenFisca_Web_API-8.2.0.data/data/share/openfisca/openfisca-web-api/LICENSE
OpenFisca_Web_API-8.2.0.data/data/share/openfisca/openfisca-web-api/README.md
OpenFisca_Web_API-8.2.0.data/data/share/openfisca/openfisca-web-api/development-france.ini
OpenFisca_Web_API-8.2.0.data/data/share/openfisca/openfisca-web-api/development-tunisia.ini
OpenFisca_Web_API-8.2.0.data/data/share/openfisca/openfisca-web-api/test.ini
OpenFisca_Web_API-8.2.0.dist-info/METADATA
OpenFisca_Web_API-8.2.0.dist-info/RECORD
OpenFisca_Web_API-8.2.0.dist-info/WHEEL
OpenFisca_Web_API-8.2.0.dist-info/entry_points.txt
OpenFisca_Web_API-8.2.0.dist-info/top_level.txt
openfisca_web_api/__init__.py
openfisca_web_api/application.py
openfisca_web_api/contexts.py
openfisca_web_api/conv.py
openfisca_web_api/environment.py
openfisca_web_api/model.py
openfisca_web_api/urls.py
openfisca_web_api/wsgihelpers.py
openfisca_web_api/controllers/__init__.py
openfisca_web_api/controllers/calculate.py
openfisca_web_api/controllers/entities.py
openfisca_web_api/controllers/field.py
openfisca_web_api/controllers/formula.py
openfisca_web_api/controllers/parameters.py
openfisca_web_api/controllers/reforms.py
openfisca_web_api/controllers/simulate.py
openfisca_web_api/controllers/swagger.py
openfisca_web_api/controllers/variables.py
openfisca_web_api/scripts/__init__.py
openfisca_web_api/scripts/serve.py
