Metadata-Version: 2.1
Name: OpenFisca-Web-API
Version: 8.2.0
Summary: Web API for OpenFisca
Home-page: https://github.com/openfisca/openfisca-web-api
Author: OpenFisca Team
Author-email: contact@openfisca.fr
License: http://www.fsf.org/licensing/licenses/agpl-3.0.html
Keywords: api benefit microsimulation server social tax web
Platform: UNKNOWN
Classifier: Development Status :: 2 - Pre-Alpha
Classifier: Environment :: Web Environment
Classifier: License :: OSI Approved :: GNU Affero General Public License v3
Classifier: Operating System :: POSIX
Classifier: Programming Language :: Python
Classifier: Topic :: Scientific/Engineering :: Information Analysis
Classifier: Topic :: Internet :: WWW/HTTP :: WSGI :: Server
Provides-Extra: test
Provides-Extra: tracker
Provides-Extra: paster
Requires-Dist: Babel (>=0.9.4)
Requires-Dist: Biryani[datetimeconv] (>=0.10.4)
Requires-Dist: OpenFisca-Core (<24.0,>=23)
Requires-Dist: PasteDeploy
Requires-Dist: WebError (>=0.10)
Requires-Dist: WebOb (>=1.1)
Requires-Dist: enum34 (>=1.1.6)
Provides-Extra: paster
Requires-Dist: PasteScript; extra == 'paster'
Provides-Extra: test
Requires-Dist: flake8; extra == 'test'
Requires-Dist: nose; extra == 'test'
Provides-Extra: tracker
Requires-Dist: openfisca-tracker; extra == 'tracker'
